LICENSE.txt
README.md
setup.cfg
setup.py
best/__init__.py
best/integration/__init__.py
best/unit/__init__.py
best/unit/conftest.py
best/unit/test_glue_session.py
best/unit/test_glue_session_demo.py
best/unit/test_session_apis.py
hyperpod_cheverification_training.egg-info/PKG-INFO
hyperpod_cheverification_training.egg-info/SOURCES.txt
hyperpod_cheverification_training.egg-info/dependency_links.txt
hyperpod_cheverification_training.egg-info/top_level.txt