Metadata-Version: 2.1
Name: hyperpod-cheverification-training
Version: 100.0.0
Summary: HyperPod CHE verification training package
Home-page: https://github.com/chehaoha/hyperpod-cheverification-training
Author: chehaoha
Author-email: chehaoha@amazon.com
License: Apache License 2.0
Platform: UNKNOWN
Classifier: Programming Language :: Python :: 3
Classifier: License :: OSI Approved :: Apache Software License
Classifier: Operating System :: OS Independent
Requires-Python: >=3.6
License-File: LICENSE.txt
